LICENSE
README.md
VERSION
pyproject.toml
ocm_python_client/__init__.py
ocm_python_client/api_client.py
ocm_python_client/configuration.py
ocm_python_client/exceptions.py
ocm_python_client/model_utils.py
ocm_python_client/rest.py
ocm_python_client/api/__init__.py
ocm_python_client/api/default_api.py
ocm_python_client/apis/__init__.py
ocm_python_client/model/__init__.py
ocm_python_client/model/add_on.py
ocm_python_client/model/add_on_config.py
ocm_python_client/model/add_on_environment_variable.py
ocm_python_client/model/add_on_install_mode.py
ocm_python_client/model/add_on_installation.py
ocm_python_client/model/add_on_installation_billing.py
ocm_python_client/model/add_on_installation_parameter.py
ocm_python_client/model/add_on_installation_state.py
ocm_python_client/model/add_on_namespace.py
ocm_python_client/model/add_on_parameter.py
ocm_python_client/model/add_on_parameter_option.py
ocm_python_client/model/add_on_requirement.py
ocm_python_client/model/add_on_requirement_status.py
ocm_python_client/model/add_on_secret_propagation.py
ocm_python_client/model/add_on_sub_operator.py
ocm_python_client/model/add_on_version.py
ocm_python_client/model/additional_catalog_source.py
ocm_python_client/model/addon_upgrade_policy.py
ocm_python_client/model/addon_upgrade_policy_state.py
ocm_python_client/model/admin_credentials.py
ocm_python_client/model/alert_info.py
ocm_python_client/model/alert_severity.py
ocm_python_client/model/alerts_info.py
ocm_python_client/model/api_clusters_mgmt_v1_addons_addon_id_versions_get200_response.py
ocm_python_client/model/api_clusters_mgmt_v1_addons_get200_response.py
ocm_python_client/model/api_clusters_mgmt_v1_aws_infrastructure_access_roles_get200_response.py
ocm_python_client/model/api_clusters_mgmt_v1_aws_inquiries_machine_types_post200_response.py
ocm_python_client/model/api_clusters_mgmt_v1_aws_inquiries_regions_post200_response.py
ocm_python_client/model/api_clusters_mgmt_v1_aws_inquiries_sts_credential_requests_get200_response.py
openshift_cluster_management_python_client.egg-info/PKG-INFO
openshift_cluster_management_python_client.egg-info/SOURCES.txt
openshift_cluster_management_python_client.egg-info/dependency_links.txt
openshift_cluster_management_python_client.egg-info/requires.txt
openshift_cluster_management_python_client.egg-info/top_level.txt