Metadata-Version: 2.1
Name: openshift-cluster-management-python-client
Version: 2.0.0
Summary: A python client for https://api.openshift.com/api/ APIs
Author-email: Meni Yakove <myakove@gmail.com>, Ruth Netser <rnetser@gmail.com>
Project-URL: Homepage, https://github.com/RedHatQE/openshift-cluster-management-python-client
Project-URL: Download, https://pypi.org/project/openshift-cluster-management-python-client/
Project-URL: Documentation, https://github.com/RedHatQE/openshift-cluster-management-python-client/blob/main/README.md
Keywords: Openshift,OCM
Classifier: Programming Language :: Python :: 3
Classifier: Operating System :: OS Independent
Requires-Python: >=3.9
License-File: LICENSE
Requires-Dist: urllib3>=1.25.3
Requires-Dist: python-dateutil
